{"\/images\/sampledata\/parks\/landscape\/727px_rainforest_bluemountainsnsw.jpg":{"940":{"box-left":50,"box-top":41,"box-width":400,"box-height":330},"max":{"box-left":50,"box-top":41,"box-width":400,"box-height":330}},"\/images\/sampledata\/fruitshop\/bananas_2.jpg":{"240":{"box-left":99,"box-top":67,"box-width":124,"box-height":146},"max":{"box-left":0,"box-top":0,"box-width":223,"box-height":262},"940":{"box-left":0,"box-top":0,"box-width":0,"box-height":0},"360":{"box-left":0,"box-top":0,"box-width":223,"box-height":262}},"\/images\/sampledata\/parks\/banner_cradle.jpg":{"240":{"box-left":112,"box-top":5,"box-width":379,"box-height":108},"max":{"box-left":112,"box-top":5,"box-width":379,"box-height":108},"940":{"box-left":112,"box-top":5,"box-width":379,"box-height":108}},"\/images\/pexels-photo-639078.jpeg":{"940":{"box-left":190,"box-top":112,"box-width":216,"box-height":94},"max":{"box-left":190,"box-top":112,"box-width":216,"box-height":94}},"\/images\/pexels-photo-1116613.jpeg":{"940":{"box-left":97,"box-top":150,"box-width":904,"box-height":603},"max":{"box-left":97,"box-top":150,"box-width":904,"box-height":603}}}